cachew/__init__.py
cachew/common.py
cachew/compat.py
cachew/experimental.py
cachew/extra.py
cachew/legacy.py
cachew/logging_helper.py
cachew/py.typed
cachew/pytest.py
cachew/utils.py
cachew/backend/common.py
cachew/backend/file.py
cachew/backend/sqlite.py
cachew/marshall/cachew.py
cachew/marshall/common.py
cachew/tests/marshall.py
cachew/tests/test_cachew.py
cachew/tests/test_future_annotations.py
cachew/tests/test_resolve_type_parameters.py
cachew/tests/utils.py
cachew-0.22.20251013.dist-info/METADATA
cachew-0.22.20251013.dist-info/WHEEL
cachew-0.22.20251013.dist-info/licenses/LICENSE.txt
cachew-0.22.20251013.dist-info/RECORD
