Metadata-Version: 2.4
Name: cachew
Version: 0.22.20251013
Project-URL: Homepage, https://github.com/karlicoss/cachew
Author-email: "Dima Gerasimov (@karlicoss)" <karlicoss@gmail.com>
Maintainer-email: "Dima Gerasimov (@karlicoss)" <karlicoss@gmail.com>
License: The MIT License (MIT)
License-File: LICENSE.txt
Requires-Python: >=3.12
Requires-Dist: orjson
Requires-Dist: platformdirs
Requires-Dist: sqlalchemy>=1.0
Requires-Dist: typing-extensions
Provides-Extra: optional
Requires-Dist: colorlog; extra == 'optional'
